{
  "description": "Model for switch",
  "$ref": "#definitions/switch",
  "definitions": {
    "switch": {
      "type": "object",
      "properties": {
        "meta": {
          "type": "object",
          "properties": {
            "part_number": {
              "type": "string"
            },
            "distributor": {
              "type": "string"
            },
            "quantity": {
              "type": "number"
            }
          }
        },
        "location": {
          "type": "object",
          "properties": {
            "value": {
              "type": "number"
            },
            "strValue": {
              "type": "string"
            }
          }
        },
        "use": {
          "type": "object",
          "properties": {
            "value": {
              "type": "number"
            },
            "strValue": {
              "type": "string"
            }
          }
        },
        "current_rating": {
          "type": "object",
          "properties": {
            "value": {
              "type": "number"
            },
            "strValue": {
              "type": "string"
            }
          }
        },
        "datasheet": {
          "type": "object",
          "properties": {
            "value": {
              "type": "number"
            },
            "strValue": {
              "type": "string"
            }
          }
        }
      },
      "required": [],
      "title": "switch"
    }
  }
}